pyapi_memedeck/__init__.py
pyapi_memedeck/apiclient.py
pyapi_memedeck-0.0.1.dist-info/METADATA
pyapi_memedeck-0.0.1.dist-info/WHEEL
pyapi_memedeck-0.0.1.dist-info/licenses/LICENSE
pyapi_memedeck-0.0.1.dist-info/RECORD
