Metadata-Version: 2.4
Name: pyapi_memedeck
Version: 0.0.1
Summary: Client library for interacting with MemeDeck's public API
Project-URL: Homepage, https://github.com/holium/pyapi-memedeck
Project-URL: Issues, https://github.com/holium/pyapi-memedeck/issues
Author-email: Holium <daniel@holium.com>
License-Expression: MIT
License-File: LICENSE
Classifier: Operating System :: OS Independent
Classifier: Programming Language :: Python :: 3
Classifier: Programming Language :: Python :: 3.12
Requires-Python: ~=3.12
Requires-Dist: requests>=2.31.0
